[
    {
        "Token Count": 2145,
        "TimeStamp": 0.9452898502349854,
        "Model": "GPT 4o Mini"
    },
    {
        "Token Count": 2360,
        "TimeStamp": 0.8215000629425049,
        "Model": "GPT 4o Mini"
    },
    {
        "Token Count": 1311,
        "TimeStamp": 0.5612680912017822,
        "Model": "GPT 4o Mini"
    },
    {
        "Token Count": 1124,
        "TimeStamp": 0.4953422546386719,
        "Model": "GPT 4o Mini"
    },
    {
        "Token Count": 2281,
        "TimeStamp": 0.6729929447174072,
        "Model": "GPT 4o Mini"
    },
    {
        "Token Count": 1701,
        "TimeStamp": 1.060533046722412,
        "Model": "GPT 4o Mini"
    },
    {
        "Token Count": 2352,
        "TimeStamp": 0.7212698459625244,
        "Model": "GPT 4o Mini"
    },
    {
        "Token Count": 2982,
        "TimeStamp": 1.7844841480255127,
        "Model": "GPT 4o Mini"
    },
    {
        "Token Count": 1084,
        "TimeStamp": 1.3873300552368164,
        "Model": "GPT 4o Mini"
    },
    {
        "Token Count": 1692,
        "TimeStamp": 1.335191249847412,
        "Model": "GPT 4o Mini"
    },
    {
        "Token Count": 1567,
        "TimeStamp": 0.7124180793762207,
        "Model": "GPT 4o Mini"
    },
    {
        "Token Count": 1434,
        "TimeStamp": 2.434739828109741,
        "Model": "GPT 4o Mini"
    },
    {
        "Token Count": 2002,
        "TimeStamp": 2.255028009414673,
        "Model": "GPT 4o Mini"
    },
    {
        "Token Count": 2454,
        "TimeStamp": 1.6348938941955566,
        "Model": "GPT 4o Mini"
    },
    {
        "Token Count": 1844,
        "TimeStamp": 4.19976806640625,
        "Model": "GPT 4o Mini"
    },
    {
        "Token Count": 2444,
        "TimeStamp": 2.096212863922119,
        "Model": "GPT 4o Mini"
    },
    {
        "Token Count": 2762,
        "TimeStamp": 2.972835063934326,
        "Model": "GPT 4o Mini"
    },
    {
        "Token Count": 1498,
        "TimeStamp": 0.7688632011413574,
        "Model": "GPT 4o Mini"
    },
    {
        "Token Count": 1660,
        "TimeStamp": 0.8918709754943848,
        "Model": "GPT 4o Mini"
    },
    {
        "Token Count": 1546,
        "TimeStamp": 1.0986733436584473,
        "Model": "GPT 4o Mini"
    },
    {
        "Token Count": 1537,
        "TimeStamp": 0.4849410057067871,
        "Model": "GPT 4o Mini"
    },
    {
        "Token Count": 1259,
        "TimeStamp": 0.8109221458435059,
        "Model": "GPT 4o Mini"
    },
    {
        "Token Count": 5182,
        "TimeStamp": 0.9750349521636963,
        "Model": "GPT 4o Mini"
    },
    {
        "Token Count": 1880,
        "TimeStamp": 1.985386848449707,
        "Model": "GPT 4o Mini"
    },
    {
        "Token Count": 2132,
        "TimeStamp": 3.1813313961029053,
        "Model": "GPT 4o Mini"
    },
    {
        "Token Count": 2982,
        "TimeStamp": 2.102756977081299,
        "Model": "GPT 4o Mini"
    },
    {
        "Token Count": 1097,
        "TimeStamp": 2.4915778636932373,
        "Model": "GPT 4o Mini"
    },
    {
        "Token Count": 2397,
        "TimeStamp": 2.573111057281494,
        "Model": "GPT 4o Mini"
    },
    {
        "Token Count": 2733,
        "TimeStamp": 2.827011823654175,
        "Model": "GPT 4o Mini"
    },
    {
        "Token Count": 993,
        "TimeStamp": 1.1665990352630615,
        "Model": "GPT 4o Mini"
    },
    {
        "Token Count": 1570,
        "TimeStamp": 1.5238220691680908,
        "Model": "GPT 4o Mini"
    },
    {
        "Token Count": 1721,
        "TimeStamp": 0.5554208755493164,
        "Model": "GPT 4o Mini"
    },
    {
        "Token Count": 3122,
        "TimeStamp": 2.8566269874572754,
        "Model": "GPT 4o Mini"
    },
    {
        "Token Count": 2695,
        "TimeStamp": 3.8963677883148193,
        "Model": "GPT 4o Mini"
    },
    {
        "Token Count": 2171,
        "TimeStamp": 1.2139148712158203,
        "Model": "GPT 4o Mini"
    },
    {
        "Token Count": 1781,
        "TimeStamp": 1.3154950141906738,
        "Model": "GPT 4o Mini"
    },
    {
        "Token Count": 993,
        "TimeStamp": 0.9153447151184082,
        "Model": "GPT 4o Mini"
    },
    {
        "Token Count": 1975,
        "TimeStamp": 2.19337797164917,
        "Model": "GPT 4o Mini"
    },
    {
        "Token Count": 848,
        "TimeStamp": 4.125139951705933,
        "Model": "GPT 4o Mini"
    },
    {
        "Token Count": 822,
        "TimeStamp": 3.2857491970062256,
        "Model": "GPT 4o Mini"
    },
    {
        "Token Count": 1954,
        "TimeStamp": 7.657287836074829,
        "Model": "GPT 4o Mini"
    },
    {
        "Token Count": 1833,
        "TimeStamp": 4.060802936553955,
        "Model": "GPT 4o Mini"
    },
    {
        "Token Count": 2246,
        "TimeStamp": 1.8920769691467285,
        "Model": "GPT 4o Mini"
    },
    {
        "Token Count": 685,
        "TimeStamp": 1.6765539646148682,
        "Model": "GPT 4o Mini"
    },
    {
        "Token Count": 1456,
        "TimeStamp": 1.0356950759887695,
        "Model": "GPT 4o Mini"
    },
    {
        "Token Count": 1738,
        "TimeStamp": 1.6873667240142822,
        "Model": "GPT 4o Mini"
    },
    {
        "Token Count": 1661,
        "TimeStamp": 1.4913370609283447,
        "Model": "GPT 4o Mini"
    },
    {
        "Token Count": 4133,
        "TimeStamp": 1.699429988861084,
        "Model": "GPT 4o Mini"
    },
    {
        "Token Count": 1236,
        "TimeStamp": 0.9409630298614502,
        "Model": "GPT 4o Mini"
    },
    {
        "Token Count": 777,
        "TimeStamp": 0.8603448867797852,
        "Model": "GPT 4o Mini"
    },
    {
        "Token Count": 0,
        "TimeStamp": 1.350067138671875,
        "Model": "GPT 4o Mini"
    },
    {
        "Token Count": 0,
        "TimeStamp": 1.0518317222595215,
        "Model": "GPT 4o Mini"
    },
    {
        "Token Count": 0,
        "TimeStamp": 1.0060033798217773,
        "Model": "GPT 4o Mini"
    },
    {
        "Token Count": 0,
        "TimeStamp": 0.7582299709320068,
        "Model": "GPT 4o Mini"
    },
    {
        "Token Count": 0,
        "TimeStamp": 1.0354013442993164,
        "Model": "GPT 4o Mini"
    },
    {
        "Token Count": 0,
        "TimeStamp": 0.7467985153198242,
        "Model": "GPT 4o Mini"
    },
    {
        "Token Count": 0,
        "TimeStamp": 1.0828936100006104,
        "Model": "GPT 4o Mini"
    },
    {
        "Token Count": 0,
        "TimeStamp": 0.9632003307342529,
        "Model": "GPT 4o Mini"
    }
]